dmcview/__init__.py
dmcview/__main__.py
dmcview/accele3D_signal_manger.py
dmcview/acceleration.py
dmcview/cli.py
dmcview/compass.py
dmcview/py.typed
dmcview/simulator.py
dmc_view-0.3.3.dist-info/AUTHORS.md
dmc_view-0.3.3.dist-info/LICENSE
dmc_view-0.3.3.dist-info/METADATA
dmc_view-0.3.3.dist-info/WHEEL
dmc_view-0.3.3.dist-info/entry_points.txt
dmc_view-0.3.3.dist-info/RECORD
