Metadata-Version: 2.3
Name: dmc-view
Version: 0.3.3
Summary: Digital Magnatic Compass View
License: AGPL-3.0-only
Keywords: digital magnatic view,dmc
Author: Iso
Maintainer: Iso
Requires-Python: >=3.8
Classifier: Development Status :: 5 - Production/Stable
Classifier: Intended Audience :: Manufacturing
Classifier: Intended Audience :: End Users/Desktop
Classifier: License :: OSI Approved :: GNU Affero General Public License v3
Classifier: Natural Language :: English
Classifier: Operating System :: Unix
Classifier: Operating System :: POSIX :: Linux
Classifier: Operating System :: MacOS
Classifier: Programming Language :: Python :: 3 :: Only
Classifier: Programming Language :: Python :: 3.8
Classifier: Programming Language :: Python :: 3.9
Classifier: Programming Language :: Python :: 3.10
Classifier: Programming Language :: Python :: 3.11
Classifier: Programming Language :: Python :: 3.12
Classifier: Programming Language :: Python :: 3.13
Classifier: Topic :: Desktop Environment
Provides-Extra: docs
Provides-Extra: test
Requires-Dist: Sphinx (<=8.2.3) ; (python_version >= "3.11" and python_version <= "3.14") and (extra == "docs")
Requires-Dist: matplotlib (>=3.10.1) ; python_version >= "3.10" and python_version <= "3.13"
Requires-Dist: pyside6 (<=6.9.1) ; python_version >= "3.9" and python_version <= "3.13"
Requires-Dist: pyside6 (>=6.6.1) ; python_version >= "3.8" and python_version <= "3.12"
Requires-Dist: pytest (>=8.4.0) ; (python_version >= "3.9" and python_version <= "3.14") and (extra == "test")
Requires-Dist: pytest-cov (>=6) ; (python_version >= "3.9" and python_version <= "3.13") and (extra == "test")
Requires-Dist: pytest-mock (>=3.14.0) ; (python_version >= "3.9" and python_version <= "3.14") and (extra == "test")
Requires-Dist: sphinx-autobuild (==2024.10.3) ; (python_version >= "3.9" and python_version <= "3.14") and (extra == "docs")
Requires-Dist: sphinx-autodoc-typehints (<=3.2.0) ; (python_version >= "3.11" and python_version <= "3.14") and (extra == "docs")
Requires-Dist: sphinx-inline-tabs (==2023.4.21) ; (python_version >= "3.8" and python_version <= "3.14") and (extra == "docs")
Requires-Dist: sphinx-rtd-theme (<=3.0.2) ; (python_version >= "3.8" and python_version <= "3.14") and (extra == "docs")
Requires-Dist: sphinxcontrib-mermaid (<=1.0.0) ; (python_version >= "3.8" and python_version <= "3.14") and (extra == "docs")
Requires-Dist: sphinxcontrib-spelling (<=8.0.1) ; (python_version >= "3.10" and python_version <= "3.14") and (extra == "docs")
Project-URL: Bug Tracker, https://github.com/Issamricin/dmc-view/issues
Project-URL: CI: Github Actions, https://github.com/Issamricin/dmc-view/actions
Project-URL: Changelog, https://github.com/Issamricin/dmc-view/blob/master/CHANGELOG.rst
Project-URL: Code of Conduct, https://github.com/Issamricin/dmc-view/blob/master/CONTRIBUTING.md
Project-URL: Documentation, https://dmc-view.readthedocs.io/
Project-URL: Source Code, https://github.com/Issamricin/dmc-view
